{
  "base_risk_percent": 0.02,
  "max_drawdown": 0.2,
  "drawdown_reduction_threshold": 0.15,
  "base_confidence_threshold": 0.6,
  "min_risk_reward_ratio": 2.0,
  "base_atr_sl_multiplier": 1.0,
  "base_atr_tp_multiplier": 2.0,
  "kelly_fraction": 0.5,
  "max_risk_per_trade": 0.05,
  "max_positions": 1,
  "contract_size": 100.0,
  "pip_value_per_lot": 10.0,
  "pip_multiplier": 100.0,
  "min_lot_size": 0.01,
  "base_leverage": 2000.0,
  "time_filters": {
    "blocked_hours_before_news": 0.5,
    "blocked_hours_after_news": 0.5,
    "blocked_hours_weekend_close": 4,
    "blocked_hours_weekend_open": 2
  }
}